app_name_generator/__init__.py
app_name_generator/__main__.py
app_name_generator/availability.py
app_name_generator/dictionary.py
app_name_generator/generator.py
app_name_generator/nouns.py
app_name_generator/utils.py
app_name_generator-0.1.1.dist-info/METADATA
app_name_generator-0.1.1.dist-info/WHEEL
app_name_generator-0.1.1.dist-info/entry_points.txt
app_name_generator-0.1.1.dist-info/top_level.txt
app_name_generator-0.1.1.dist-info/RECORD
