Metadata-Version: 2.1
Name: app-name-generator
Version: 0.1.1
Summary: Generate available app names
Home-page: UNKNOWN
License: UNKNOWN
Platform: UNKNOWN
Requires-Dist: dnspython
